pelican_vimeo/__init__.py
pelican_vimeo/vimeo.py
pelican_vimeo-0.1.2.dist-info/DESCRIPTION.rst
pelican_vimeo-0.1.2.dist-info/METADATA
pelican_vimeo-0.1.2.dist-info/RECORD
pelican_vimeo-0.1.2.dist-info/WHEEL
pelican_vimeo-0.1.2.dist-info/metadata.json
pelican_vimeo-0.1.2.dist-info/top_level.txt
pelican_vimeo-0.1.2.dist-info/zip-safe
